LICENSE
odd_models/__init__.py
odd_models/api_client/__init__.py
odd_models/api_client/api/__init__.py
odd_models/api_client/api/open_data_discovery_ingestion_api.py
odd_models/api_client/http_client.py
odd_models/api_client/open_data_discovery_ingestion_api.py
odd_models/api_client/v2/__init__.py
odd_models/api_client/v2/errors.py
odd_models/api_client/v2/odd_api_client.py
odd_models/discovery/__init__.py
odd_models/discovery/data_assets/__init__.py
odd_models/discovery/data_assets/aws_lambda.py
odd_models/discovery/data_assets/data_asset.py
odd_models/discovery/data_assets/data_asset_list.py
odd_models/discovery/data_assets/database.py
odd_models/discovery/data_assets/s3_artifact.py
odd_models/discovery/data_source.py
odd_models/discovery/helper.py
odd_models/integrator.py
odd_models/logger.py
odd_models/models/__init__.py
odd_models/models/metrics.py
odd_models/models/models.py
odd_models/sql_parser.py
odd_models/utils.py
odd_models-2.0.51.dist-info/LICENSE
odd_models-2.0.51.dist-info/METADATA
odd_models-2.0.51.dist-info/WHEEL
odd_models-2.0.51.dist-info/RECORD
