Metadata-Version: 2.1
Name: odd-models
Version: 2.0.51
Summary: Open Data Discovery Models
Home-page: https://github.com/opendatadiscovery/odd-models-package
License: Apache-2.0
Keywords: odd-models,odd_models,opendatadiscovery
Author: Open Data Discovery
Author-email: pypi@opendatadiscovery.org
Requires-Python: >=3.9,<4.0
Classifier: License :: OSI Approved :: Apache Software License
Classifier: Programming Language :: Python :: 3
Classifier: Programming Language :: Python :: 3.9
Classifier: Programming Language :: Python :: 3.10
Classifier: Programming Language :: Python :: 3.11
Requires-Dist: funcy (>=2.0,<3.0)
Requires-Dist: loguru (>=0.7.2,<0.8.0)
Requires-Dist: oddrn-generator (>=0.1.101,<0.2.0)
Requires-Dist: pydantic (>=2.7.0,<3.0.0)
Requires-Dist: requests (>=2.31.0,<3.0.0)
Requires-Dist: sql-metadata (>=2.6.0,<3.0.0)
Requires-Dist: sqllineage (>=1.4.7,<2.0.0)
Requires-Dist: sqlparse (>=0.5.0,<0.6.0)
Project-URL: Repository, https://github.com/opendatadiscovery/odd-models-package
